parcoords/__init__.py
parcoords/parcoords.py
parcoords-0.1.4.dist-info/LICENSE.txt
parcoords-0.1.4.dist-info/METADATA
parcoords-0.1.4.dist-info/WHEEL
parcoords-0.1.4.dist-info/top_level.txt
parcoords-0.1.4.dist-info/RECORD
