Metadata-Version: 2.1
Name: parcoords
Version: 0.1.4
Summary: Parallel coordinates plotting
Home-page: https://github.com/VoigtPeter/parcoords
Author: Peter Voigt
License: MIT
Project-URL: Documentation, https://voigtpeter.github.io/parcoords/index.html
Project-URL: Source, https://github.com/VoigtPeter/parcoords
Keywords: parallel coordinates,parallel-coordinates,plot,hyperparameter,visualization
Classifier: Programming Language :: Python :: 3
Classifier: License :: OSI Approved :: MIT License
Classifier: Operating System :: OS Independent
Requires-Python: >=3.6
License-File: LICENSE.txt
Requires-Dist: matplotlib
Requires-Dist: numpy
